oftools_compile/Clear.py
oftools_compile/Context.py
oftools_compile/Grouping.py
oftools_compile/Log.py
oftools_compile/Main.py
oftools_compile/Profile.py
oftools_compile/Report.py
oftools_compile/Source.py
oftools_compile/__init__.py
oftools_compile/enums/ErrorEnum.py
oftools_compile/enums/LogEnum.py
oftools_compile/enums/__init__.py
oftools_compile/handlers/FileHandler.py
oftools_compile/handlers/ShellHandler.py
oftools_compile/handlers/__init__.py
oftools_compile/jobs/CompileJob.py
oftools_compile/jobs/DeployJob.py
oftools_compile/jobs/Job.py
oftools_compile/jobs/JobFactory.py
oftools_compile/jobs/SetupJob.py
oftools_compile/jobs/__init__.py
oftools_compile-1.4.1.dist-info/LICENSE.md
oftools_compile-1.4.1.dist-info/METADATA
oftools_compile-1.4.1.dist-info/WHEEL
oftools_compile-1.4.1.dist-info/entry_points.txt
oftools_compile-1.4.1.dist-info/pbr.json
oftools_compile-1.4.1.dist-info/top_level.txt
oftools_compile-1.4.1.dist-info/RECORD
