Metadata-Version: 2.1
Name: oftools-compile
Version: 1.4.1
Summary: A general-purpose build tool that is designed to be flexible to support compilers and tools available in the OpenFrame environment.
Home-page: https://github.com/tmaxsoft-us/oftools_compile
Author: TmaxSoft
Author-email: tfsadmin@tmaxsoft.com
License: CC4.0-BY-NC-SA
Project-URL: Bug Reports, https://github.com/tmaxsoft-us/oftools_compile/issues
Project-URL: Documentation, https://github.com/tmaxsoft-us/oftools_docs/tree/master/compile
Project-URL: Source Code, https://github.com/tmaxsoft-us/oftools_compile/tree/master
Platform: UNKNOWN
Classifier: Development Status :: 5 - Production/Stable
Classifier: Environment :: Console
Classifier: Intended Audience :: Developers
Classifier: Intended Audience :: Information Technology
Classifier: License :: Other/Proprietary License
Classifier: Natural Language :: English
Classifier: Operating System :: POSIX :: Linux
Classifier: Programming Language :: Python
Classifier: Programming Language :: Python :: 3.6
Classifier: Programming Language :: Python :: 3.7
Classifier: Programming Language :: Python :: 3.8
Classifier: Programming Language :: Python :: 3.9
Classifier: Topic :: Scientific/Engineering
Classifier: Topic :: System :: Hardware :: Mainframes
Requires-Python: <4,>=3.6
Requires-Dist: coverage
Requires-Dist: pbr
Requires-Dist: pytest
Requires-Dist: setuptools
Requires-Dist: setuptools-scm
Requires-Dist: versioneer
Requires-Dist: wheel
